README.rst
distribute_setup.py
setup.py
predestinate/__init__.py
predestinate/gods.py
predestinate.egg-info/PKG-INFO
predestinate.egg-info/SOURCES.txt
predestinate.egg-info/dependency_links.txt
predestinate.egg-info/not-zip-safe
predestinate.egg-info/top_level.txt
tests/__init__.py
tests/predestinate_tests.py