Metadata-Version: 1.1
Name: predestinate
Version: 0.1.3
Summary: Script mouse and keyboard actions via xautomation in GNU/Linux
Home-page: https://github.com/oddshocks/predestinate
Author: David Gay
Author-email: oddshocks@riseup.net
License: GPLv3+
Keywords: xautomation wrapper X mouse keyboard scripting
Platform: UNKNOWN
Classifier: Programming Language :: Python :: 2.7
Classifier: Development Status :: 3 - Alpha
Classifier: License :: OSI Approved :: GNU General Public License v3 or later (GPLv3+)
Classifier: Operating System :: Unix
